sqlschm/__init__.py
sqlschm/generator.py
sqlschm/lexer.py
sqlschm/parser.py
sqlschm/py.typed
sqlschm/sql.py
sqlschm/tok.py
sqlschm-0.8.0.dist-info/entry_points.txt
sqlschm-0.8.0.dist-info/LICENSE
sqlschm-0.8.0.dist-info/WHEEL
sqlschm-0.8.0.dist-info/METADATA
sqlschm-0.8.0.dist-info/RECORD
