Metadata-Version: 2.1
Name: sqlschm
Version: 0.8.0
Summary: A SQLite Schema parser
Home-page: https://github.com/coast-team/sqlschm
License: Apache-2.0
Author: Victorien Elvinger
Author-email: victorien.elvinger@inria.fr
Requires-Python: >=3.10,<4.0
Classifier: License :: OSI Approved :: Apache Software License
Classifier: Programming Language :: Python :: 3
Classifier: Programming Language :: Python :: 3.10
Classifier: Programming Language :: Python :: 3.11
Project-URL: Repository, https://github.com/coast-team/sqlschm
